syside_license/__init__.py
syside_license/__main__.py
syside_license/_syside_license_core.pyd
syside_license/_syside_license_core.pyi
syside_license/py.typed
syside_license-0.3.4.dist-info/METADATA
syside_license-0.3.4.dist-info/WHEEL
syside_license-0.3.4.dist-info/entry_points.txt
syside_license-0.3.4.dist-info/licenses/LICENSE.txt
syside_license-0.3.4.dist-info/licenses/third-party-licenses.md
syside_license-0.3.4.dist-info/RECORD
