Metadata-Version: 2.4
Name: syside_license
Version: 0.3.4
Classifier: Programming Language :: Rust
Classifier: Programming Language :: Python :: Implementation :: CPython
Classifier: Programming Language :: Python :: Implementation :: PyPy
Classifier: Programming Language :: Python :: 3.9
Classifier: Programming Language :: Python :: 3.10
Classifier: Programming Language :: Python :: 3.11
Classifier: Programming Language :: Python :: 3.12
Classifier: Programming Language :: Python :: 3.13
Classifier: Programming Language :: Python :: 3.14
Classifier: Intended Audience :: Developers
Classifier: Topic :: Scientific/Engineering
License-File: LICENSE.txt
License-File: third-party-licenses.md
Summary: License checker for the Syside tools.
Keywords: syside
Author-email: Sensmetry <syside@sensmetry.com>
License-Expression: LicenseRef-Proprietary
Requires-Python: >=3.8
Project-URL: Homepage, https://sensmetry.com/syside
Project-URL: Issues, https://forum.sensmetry.com/c/syside/bug-reports/5
